text2music/__init__.py
text2music/experimental/__init__.py
text2music/experimental/mubert__.py
text2music/output/__init__.py
text2music/output/outputs__.py
text2music-0.1.3.dist-info/METADATA
text2music-0.1.3.dist-info/WHEEL
text2music-0.1.3.dist-info/top_level.txt
text2music-0.1.3.dist-info/RECORD
