Metadata-Version: 2.1
Name: text2music
Version: 0.1.3
Summary: A package for text-to-music generation
Home-page: https://github.com/NLP-Guild/text2music
Author: NLP Guild
Author-email: tao.xiang@tum.de
License: UNKNOWN
Platform: UNKNOWN
Classifier: Programming Language :: Python :: 3.8
Classifier: License :: OSI Approved :: MIT License
Requires-Dist: sentence-transformers
Requires-Dist: numpy
Requires-Dist: httpx
Requires-Dist: requests
